dicomanonymizer/__init__.py
dicomanonymizer/anonymizer.py
dicomanonymizer/dicom_anonymization_databases/__init__.py
dicomanonymizer/dicom_anonymization_databases/dicomfields_2023.py
dicomanonymizer/dicom_anonymization_databases/dicomfields_2024b.py
dicomanonymizer/dicomfields_selector.py
dicomanonymizer/format_tag.py
dicomanonymizer/simpledicomanonymizer.py
dicomanonymizer/version.py
dicom_anon-1.0.13.post2.dist-info/entry_points.txt
dicom_anon-1.0.13.post2.dist-info/WHEEL
dicom_anon-1.0.13.post2.dist-info/METADATA
dicom_anon-1.0.13.post2.dist-info/licenses/LICENSE
dicom_anon-1.0.13.post2.dist-info/RECORD
