Metadata-Version: 2.1
Name: dicom-anon
Version: 1.0.13.post2
Summary: Program to anonymize dicom files with default and custom rules
License: Apache
Author-email: Tim Cogan <tim@medcognetics.com>,Scott Chase Waggener <chase@medcognetics.com>,Laurenn Lam <laurenn.lam@kitware.com>
Requires-Python: >=3.8
Requires-Dist: pydicom
Requires-Dist: setuptools>=69.0.2
Requires-Dist: tqdm
